{
  "type": "minecraft:crafting_shapeless",
  "category": "equipment",
  "ingredients": [
    {
      "item": "super_crafting:super_netherite_axe"
    },
    {
      "item": "minecraft:netherite_axe"
    },
    {
      "item": "minecraft:netherite_axe"
    },
    {
      "item": "minecraft:nether_star"
    },
    {
      "item": "minecraft:nether_star"
    },
    {
      "item": "minecraft:end_crystal"
    },
    {
      "item": "minecraft:end_crystal"
    },
    {
      "item": "minecraft:totem_of_undying"
    },
    {
      "item": "minecraft:totem_of_undying"
    }
  ],
  "result": {
    "count": 1,
    "id": "super_crafting:ultimate_axe"
  }
}