{
  "type": "minecraft:crafting_shapeless",
  "category": "equipment",
  "ingredients": [
    {
      "item": "minecraft:bow"
    },
    {
      "item": "minecraft:bow"
    },
    {
      "item": "minecraft:bow"
    },
    {
      "item": "minecraft:feather"
    },
    {
      "item": "minecraft:feather"
    },
    {
      "item": "minecraft:feather"
    },
    {
      "item": "minecraft:string"
    },
    {
      "item": "minecraft:string"
    },
    {
      "item": "minecraft:string"
    }
  ],
  "result": {
    "count": 1,
    "id": "super_crafting:super_iron_bow"
  }
}