{
  "type": "minecraft:crafting_shapeless",
  "category": "equipment",
  "ingredients": [
    {
      "item": "minecraft:netherite_hoe"
    },
    {
      "item": "minecraft:netherite_hoe"
    },
    {
      "item": "minecraft:netherite_hoe"
    },
    {
      "item": "minecraft:netherite_block"
    },
    {
      "item": "minecraft:netherite_block"
    },
    {
      "item": "minecraft:nether_wart"
    },
    {
      "item": "minecraft:nether_wart"
    },
    {
      "item": "minecraft:chorus_fruit"
    },
    {
      "item": "minecraft:chorus_fruit"
    }
  ],
  "result": {
    "count": 1,
    "id": "super_crafting:super_netherite_hoe"
  }
}